TOPSIS101703038/Topsis.py
topsis101703038-1.0.3.dist-info/LICENSE.txt
topsis101703038-1.0.3.dist-info/METADATA
topsis101703038-1.0.3.dist-info/WHEEL
topsis101703038-1.0.3.dist-info/entry_points.txt
topsis101703038-1.0.3.dist-info/top_level.txt
topsis101703038-1.0.3.dist-info/RECORD
