Metadata-Version: 2.1
Name: topsis101703038
Version: 1.0.3
Summary: A Python package for topsis analysis.
Home-page: https://github.com/kiliumnatta/Topsis
Author: Aditya Tomar
Author-email: aditya65921@gmail.com
License: MIT
Platform: UNKNOWN
Classifier: License :: OSI Approved :: MIT License
Classifier: Programming Language :: Python :: 3
Classifier: Programming Language :: Python :: 3.7
Requires-Dist: requests
